{
  "$schema": "../gen/schemas/desktop-schema.json",
  "identifier": "default",
  "description": "Default capabilities for Pro ATT Machine",
  "windows": ["main"],
  "permissions": [
    "core:default",
    "dialog:default",
    "dialog:allow-open",
    "dialog:allow-save",
    "dialog:allow-message",
    "fs:default",
    "fs:allow-app-read",
    "fs:allow-app-write",
    "fs:allow-app-read-recursive",
    "fs:allow-app-write-recursive",
    "fs:allow-appdata-read",
    "fs:allow-appdata-write",
    "fs:allow-download-read",
    "fs:allow-download-write",
    "fs:allow-audio-read",
    "fs:allow-audio-write",
    "fs:allow-document-read",
    "fs:allow-document-write",
    "fs:allow-home-read",
    "fs:allow-home-write",
    "fs:allow-desktop-read",
    "fs:allow-desktop-write",
    "store:default",
    "notification:default",
    "notification:allow-is-permission-granted",
    "notification:allow-request-permission",
    "notification:allow-notify",
    "clipboard-manager:default",
    "clipboard-manager:allow-read-text",
    "clipboard-manager:allow-write-text",
    "shell:default",
    "shell:allow-open",
    {
      "identifier": "shell:allow-execute",
      "allow": [
        {
          "args": true,
          "name": "binaries/voice-ai-sidecar",
          "sidecar": true
        }
      ]
    },
    {
      "identifier": "shell:allow-spawn",
      "allow": [
        {
          "args": true,
          "name": "binaries/voice-ai-sidecar",
          "sidecar": true
        }
      ]
    },
    "updater:default",
    "process:default",
    "mic-recorder:default",
    "mcp-bridge:default"
  ]
}
